sl_behavior/__init__.py
sl_behavior/__init__.pyi
sl_behavior/cli.py
sl_behavior/cli.pyi
sl_behavior/log_processing.py
sl_behavior/log_processing.pyi
sl_behavior/py.typed
sl_behavior/legacy/__init__.py
sl_behavior/legacy/__init__.pyi
sl_behavior/legacy/data.py
sl_behavior/legacy/data.pyi
sl_behavior/legacy/extract.py
sl_behavior/legacy/extract.pyi
sl_behavior/legacy/io.py
sl_behavior/legacy/io.pyi
sl_behavior/legacy/parse.py
sl_behavior/legacy/parse.pyi
sl_behavior/legacy/transform.py
sl_behavior/legacy/transform.pyi
sl_behavior-3.0.0.dist-info/METADATA
sl_behavior-3.0.0.dist-info/WHEEL
sl_behavior-3.0.0.dist-info/entry_points.txt
sl_behavior-3.0.0.dist-info/licenses/LICENSE
sl_behavior-3.0.0.dist-info/RECORD
