Metadata-Version: 2.4
Name: sl-behavior
Version: 3.0.0
Summary: Provides tools for processing non-visual behavior data acquired in the Sun (NeuroAI) lab.
Project-URL: Homepage, https://github.com/Sun-Lab-NBB/sl-behavior
Project-URL: Documentation, https://sl-behavior-api-docs.netlify.app/
Author: Ivan Kondratyev, Kushaan Gupta, Natalie Yeung
Maintainer-email: Ivan Kondratyev <ik278@cornell.edu>
License:                     GNU GENERAL PUBLIC LICENSE
License-File: LICENSE
Keywords: behavior,data,processing,sunlab
Classifier: Development Status :: 5 - Production/Stable
Classifier: Intended Audience :: Developers
Classifier: License :: OSI Approved :: GNU General Public License v3 or later (GPLv3+)
Classifier: Operating System :: POSIX :: Linux
Classifier: Programming Language :: Python :: 3.11
Requires-Python: <3.12,>=3.11
Requires-Dist: ataraxis-base-utilities==3.1.0
Requires-Dist: ataraxis-communication-interface==3.2.1
Requires-Dist: ataraxis-data-structures==3.1.1
Requires-Dist: ataraxis-video-system==1.1.0
Requires-Dist: click==8.2.1
Requires-Dist: intel-cmplr-lib-rt==2025.2.0
Requires-Dist: numba==0.61.2
Requires-Dist: numpy==2.2.6
Requires-Dist: pandas==2.3.1
Requires-Dist: polars==1.32.0
Requires-Dist: pyarrow==21.0.0
Requires-Dist: scipy==1.16.1
Requires-Dist: sl-shared-assets==4.0.1
Requires-Dist: tqdm==4.67.1
Provides-Extra: conda
Requires-Dist: hatchling==1.27.0; extra == 'conda'
Requires-Dist: importlib-metadata==8.7.0; extra == 'conda'
Requires-Dist: mypy==1.17.1; extra == 'conda'
Requires-Dist: pandas-stubs==2.3.0.250703; extra == 'conda'
Requires-Dist: ruff==0.12.7; extra == 'conda'
Requires-Dist: sphinx-autodoc-typehints==3.2.0; extra == 'conda'
Requires-Dist: sphinx-click==6.0.0; extra == 'conda'
Requires-Dist: sphinx==8.2.3; extra == 'conda'
Requires-Dist: tox-uv==1.26.2; extra == 'conda'
Requires-Dist: tox==4.28.4; extra == 'conda'
Requires-Dist: twine==6.1.0; extra == 'conda'
Requires-Dist: types-tqdm==4.67.0.20250516; extra == 'conda'
Requires-Dist: uv==0.8.5; extra == 'conda'
Provides-Extra: condarun
Requires-Dist: click==8.2.1; extra == 'condarun'
Requires-Dist: intel-cmplr-lib-rt==2025.2.0; extra == 'condarun'
Requires-Dist: numba==0.61.2; extra == 'condarun'
Requires-Dist: numpy==2.2.6; extra == 'condarun'
Requires-Dist: pandas==2.3.1; extra == 'condarun'
Requires-Dist: polars==1.32.0; extra == 'condarun'
Requires-Dist: pyarrow==21.0.0; extra == 'condarun'
Requires-Dist: tqdm==4.67.1; extra == 'condarun'
Provides-Extra: dev
Requires-Dist: ataraxis-automation==5.0.0; extra == 'dev'
Requires-Dist: build==1.3.0; extra == 'dev'
Requires-Dist: hatchling==1.27.0; extra == 'dev'
Requires-Dist: importlib-metadata==8.7.0; extra == 'dev'
Requires-Dist: mypy==1.17.1; extra == 'dev'
Requires-Dist: pandas-stubs==2.3.0.250703; extra == 'dev'
Requires-Dist: ruff==0.12.7; extra == 'dev'
Requires-Dist: scipy-stubs==1.16.1.0; extra == 'dev'
Requires-Dist: sphinx-autodoc-typehints==3.2.0; extra == 'dev'
Requires-Dist: sphinx-click==6.0.0; extra == 'dev'
Requires-Dist: sphinx-rtd-dark-mode==1.3.0; extra == 'dev'
Requires-Dist: sphinx-rtd-theme==3.0.2; extra == 'dev'
Requires-Dist: sphinx==8.2.3; extra == 'dev'
Requires-Dist: tox-uv==1.26.2; extra == 'dev'
Requires-Dist: tox==4.28.4; extra == 'dev'
Requires-Dist: twine==6.1.0; extra == 'dev'
Requires-Dist: types-tqdm==4.67.0.20250516; extra == 'dev'
Requires-Dist: uv==0.8.5; extra == 'dev'
Provides-Extra: noconda
Requires-Dist: ataraxis-automation==5.0.0; extra == 'noconda'
Requires-Dist: build==1.3.0; extra == 'noconda'
Requires-Dist: scipy-stubs==1.16.1.0; extra == 'noconda'
Requires-Dist: sphinx-rtd-dark-mode==1.3.0; extra == 'noconda'
Requires-Dist: sphinx-rtd-theme==3.0.2; extra == 'noconda'
